<resources lang="zh_CN">
    <string-array name="type">
        <item>-1</item>
        <item>0</item>
        <item>0</item>
        <item>0</item>
        <item>1</item>
        <item>1</item>
        <item>1</item>
    </string-array>

    <string-array name="item">
        <item>冰块</item>
        <item>冷水</item>
        <item>常温水</item>
        <item>沸水</item>
        <item>泡奶</item>
        <item>蜂蜜水</item>
        <item>绿茶</item>
    </string-array>

    <string-array name="picture">
        <item>@mipmap/pic_bingkuai</item>
        <item>@mipmap/pic_lengshui</item>
        <item>@mipmap/pic_changwenshui</item>
        <item>@mipmap/pic_feishui</item>
        <item>@mipmap/pic_paonai</item>
        <item>@mipmap/pic_fengmishui</item>
        <item>@mipmap/pic_lvcha</item>
    </string-array>

    <string-array name="picture_2">
        <item>@mipmap/pic_bingkuai</item>
        <item>@mipmap/pic_chushui_lengshui</item>
        <item>@mipmap/pic_chushui_changwen</item>
        <item>@mipmap/pic_chushui_feishui</item>
        <item>@mipmap/pic_chushui_paonai</item>
        <item>@mipmap/pic_chushui_fengmi</item>
        <item>@mipmap/pic_chushui_lvcha</item>
    </string-array>

    <string-array name="wendu">
        <item>0</item>
        <item>6</item>
        <item>25</item>
        <item>80</item>
        <item>50</item>
        <item>50</item>
        <item>70</item>
    </string-array>

    <string-array name="chushuiliang">
        <item>50</item>
        <item>55</item>
        <item>65</item>
        <item>50</item>
        <item>70</item>
        <item>80</item>
        <item>90</item>
    </string-array>
</resources>
